{
  "project_info": {
    "project_number": "583003652433",
    "project_id": "pantryinventory-b3d7f",
    "storage_bucket": "pantryinventory-b3d7f.appspot.com"
  },
  "client": [
    {
      "client_info": {
        "mobilesdk_app_id": "1:583003652433:android:eeecc640d0e8ffecf29370",
        "android_client_info": {
          "package_name": "com.example.pantryinventory"
        }
      },
      "oauth_client": [
        {
          "client_id": "583003652433-8rfpa4kede0nkkenera6rdrjins4e2vo.apps.googleusercontent.com",
          "client_type": 3
        }
      ],
      "api_key": [
        {
          "current_key": "AIzaSyDTcE8BfeAgzdYMzdCfUwdJqAdc56FzSIM"
        }
      ],
      "services": {
        "appinvite_service": {
          "other_platform_oauth_client": [
            {
              "client_id": "583003652433-8rfpa4kede0nkkenera6rdrjins4e2vo.apps.googleusercontent.com",
              "client_type": 3
            }
          ]
        }
      }
    }
  ],
  "configuration_version": "1"
}